pipebook/__init__.py
pipebook/__main__.py
pipebook/app.py
pipebook/data.py
pipebook/doc.py
pipebook/io.py
pipebook/resources/book.png
pipebook/resources/pipbook.png
pipebook/resources/pipebook2.png
pipebook/view.py
pipebook-0.1.0.dist-info/LICENSE
pipebook-0.1.0.dist-info/WHEEL
pipebook-0.1.0.dist-info/METADATA
pipebook-0.1.0.dist-info/RECORD
